MANIFEST.in
README.md
setup.cfg
setup.py
panonoctl/__init__.py
panonoctl/panono.py
panonoctl/ssdp.py
panonoctl.egg-info/PKG-INFO
panonoctl.egg-info/SOURCES.txt
panonoctl.egg-info/dependency_links.txt
panonoctl.egg-info/requires.txt
panonoctl.egg-info/top_level.txt