Metadata-Version: 1.1
Name: panonoctl
Version: 0.5.1
Summary: Python API to interact with the PANONO 360-camera
Home-page: https://github.com/florianl/panonoctl/
Author: Florian Lehner
Author-email: dev@der-flo.net
License: Apache License 2.0
Download-URL: https://github.com/florianl/panonoctl/archive/master.tar.gz
Keywords: Panono,API 
Platform: UNKNOWN
Classifier: Development Status :: 4 - Beta
Classifier: Intended Audience :: Developers
